tests/__init__.py
tests/fancywallet_get_price_test.py
fancywallet-0.0.1.dist-info/METADATA
fancywallet-0.0.1.dist-info/WHEEL
fancywallet-0.0.1.dist-info/entry_points.txt
fancywallet-0.0.1.dist-info/top_level.txt
fancywallet-0.0.1.dist-info/RECORD
