Metadata-Version: 2.1
Name: fancywallet
Version: 0.0.1
Summary: UNKNOWN
Home-page: UNKNOWN
Author: Gui Martins
Author-email: UNKNOWN
License: UNKNOWN
Platform: UNKNOWN
Requires-Dist: click
Requires-Dist: requests
